teamleaderApiV1/__init__.py
teamleaderApiV1/client.py
teamleaderApiV1/files.py
teamleaderApiV1/methods.py
teamleaderApiV1/objects.py
teamleaderApiV1/privateLists.py
teamleaderApiV1-0.5.1.dist-info/LICENSE.txt
teamleaderApiV1-0.5.1.dist-info/METADATA
teamleaderApiV1-0.5.1.dist-info/WHEEL
teamleaderApiV1-0.5.1.dist-info/top_level.txt
teamleaderApiV1-0.5.1.dist-info/RECORD
