Metadata-Version: 2.1
Name: teamleaderApiV1
Version: 0.5.1
Summary: Python framework on top of the teamleader v1 api
Home-page: https://github.com/HeroPP/teamleaderApiV1
Download-URL: 
Author: Jaap
Author-email: jaap1@me.com
License: MIT
Platform: UNKNOWN
Classifier: Development Status :: 3 - Alpha
Classifier: Intended Audience :: Developers
Classifier: Topic :: Software Development :: Build Tools
Classifier: License :: OSI Approved :: MIT License
Classifier: Programming Language :: Python :: 3
License-File: LICENSE.txt
Requires-Dist: certifi
Requires-Dist: chardet
Requires-Dist: idna
Requires-Dist: pickle5
Requires-Dist: ratelimit
Requires-Dist: requests
Requires-Dist: urllib3
